Metadata-Version: 2.1
Name: stat-prob-dist
Version: 0.2.4
Summary: Statistical distributions - Gaussian, Binomial etc..
Home-page: UNKNOWN
Author: Amanpreet Singh
Author-email: amanpreetsingh459@gmail.com
License: MIT
Platform: UNKNOWN
